poli/__init__.py
poli/external_isolated_function_script.py
poli/objective_factory.py
poli/repository.py
poli/benchmarks/__init__.py
poli/benchmarks/guacamol.py
poli/benchmarks/pmo.py
poli/benchmarks/toy_continuous_functions_benchmark.py
poli/core/__init__.py
poli/core/abstract_benchmark.py
poli/core/abstract_black_box.py
poli/core/abstract_isolated_function.py
poli/core/abstract_problem_factory.py
poli/core/benchmark_information.py
poli/core/black_box_information.py
poli/core/data_package.py
poli/core/exceptions.py
poli/core/lambda_black_box.py
poli/core/multi_objective_black_box.py
poli/core/problem.py
poli/core/registry.py
poli/core/chemistry/__init__.py
poli/core/chemistry/environment.yml
poli/core/chemistry/tdc_black_box.py
poli/core/chemistry/tdc_isolated_function.py
poli/core/chemistry/tdc_problem.py
poli/core/chemistry/data_packages/__init__.py
poli/core/chemistry/data_packages/five_thousand_smiles.npz
poli/core/chemistry/data_packages/random_molecules_data_package.py
poli/core/proteins/__init__.py
poli/core/proteins/foldx_black_box.py
poli/core/proteins/foldx_isolated_function.py
poli/core/proteins/data_packages/__init__.py
poli/core/proteins/data_packages/foldx_supervised_data_packages.py
poli/core/proteins/data_packages/rasp_supervised_data_packages.py
poli/core/proteins/data_packages/rfp_foldx_scores.txt
poli/core/proteins/data_packages/rfp_rasp_scores.txt
poli/core/proteins/data_packages/rfp_sequences.txt
poli/core/util/__init__.py
poli/core/util/abstract_observer.py
poli/core/util/algorithm_observer_wrapper.py
poli/core/util/default_observer.py
poli/core/util/external_observer.py
poli/core/util/observer_wrapper.py
poli/core/util/alignment/__init__.py
poli/core/util/alignment/is_aligned.py
poli/core/util/batch/__init__.py
poli/core/util/batch/batch_input.py
poli/core/util/chemistry/__init__.py
poli/core/util/chemistry/string_to_molecule.py
poli/core/util/files/__init__.py
poli/core/util/files/download_files_from_github.py
poli_core-1.3.1.dist-info/METADATA
poli_core-1.3.1.dist-info/WHEEL
poli_core-1.3.1.dist-info/top_level.txt
poli_core-1.3.1.dist-info/RECORD
