Metadata-Version: 2.1
Name: poli-core
Version: 1.3.1
Summary: poli, a library of discrete objective functions
Author: Miguel González-Duque
Author-email: Miguel González-Duque <miguelgondu@gmail.com>, Simon Bartels <bartels@di.ku.dk>
License: MIT LICENSE
Project-URL: Homepage, https://github.com/MachineLearningLifeScience/poli
Keywords: optimization,molecular,discrete,proteins
Classifier: License :: OSI Approved :: MIT License
Classifier: Programming Language :: Python
Classifier: Programming Language :: Python :: 3
Classifier: Intended Audience :: Education
Classifier: Intended Audience :: Science/Research
Classifier: Topic :: Scientific/Engineering :: Bio-Informatics
Classifier: Topic :: Scientific/Engineering :: Chemistry
Classifier: Topic :: Scientific/Engineering :: Mathematics
Classifier: Topic :: Scientific/Engineering :: Artificial Intelligence
Classifier: Development Status :: 3 - Alpha
Classifier: Operating System :: MacOS
Classifier: Operating System :: Unix
Requires-Python: >=3.9
Requires-Dist: numpy<2
Requires-Dist: rdkit
Requires-Dist: selfies
Provides-Extra: dev
Requires-Dist: black; extra == "dev"
Requires-Dist: tox; extra == "dev"
Requires-Dist: pytest; extra == "dev"
Requires-Dist: bump-my-version; extra == "dev"
Requires-Dist: pre-commit; extra == "dev"
Requires-Dist: pyright; extra == "dev"
Provides-Extra: dms
Requires-Dist: pandas; extra == "dms"
Provides-Extra: dockstring
Requires-Dist: dockstring; extra == "dockstring"
Provides-Extra: docs
Requires-Dist: sphinx; extra == "docs"
Requires-Dist: furo; extra == "docs"
Provides-Extra: ehrlich
Requires-Dist: pytorch-holo; extra == "ehrlich"
Requires-Dist: botorch<=0.13.0; extra == "ehrlich"
Provides-Extra: ehrlichholo
Requires-Dist: pytorch-holo; extra == "ehrlichholo"
Provides-Extra: foldx
Requires-Dist: biopython; extra == "foldx"
Requires-Dist: python-levenshtein; extra == "foldx"
Requires-Dist: pdb-tools; extra == "foldx"
Provides-Extra: protein
Requires-Dist: biopython; extra == "protein"
Requires-Dist: python-levenshtein; extra == "protein"
Requires-Dist: pdb-tools; extra == "protein"
Provides-Extra: rmf
Requires-Dist: scipy; extra == "rmf"
Provides-Extra: rosetta_energy
Requires-Dist: biopython; extra == "rosetta-energy"
Requires-Dist: pyrosetta-installer; extra == "rosetta-energy"
Provides-Extra: tdc
Requires-Dist: pytdc==1.1.14; extra == "tdc"
